CHANGELOG.txt
LICENSE.txt
MANIFEST.in
README.txt
main.py
requirements.txt
setup.py
src/__init__.py
src/__main__.py
src/args.py
src/fplay.py
src/fprobe.py
src/main.py
src/utilities.py
tmuxradio.egg-info/PKG-INFO
tmuxradio.egg-info/SOURCES.txt
tmuxradio.egg-info/dependency_links.txt
tmuxradio.egg-info/entry_points.txt
tmuxradio.egg-info/not-zip-safe
tmuxradio.egg-info/requires.txt
tmuxradio.egg-info/top_level.txt
venv/bin/activate_this.py
venv/lib/python3.11/site-packages/_virtualenv.py
venv/lib/python3.11/site-packages/_distutils_hack/__init__.py
venv/lib/python3.11/site-packages/_distutils_hack/override.py
venv/lib/python3.11/site-packages/anyio/__init__.py
venv/lib/python3.11/site-packages/anyio/from_thread.py
venv/lib/python3.11/site-packages/anyio/lowlevel.py
venv/lib/python3.11/site-packages/anyio/pytest_plugin.py
venv/lib/python3.11/site-packages/anyio/to_process.py
venv/lib/python3.11/site-packages/anyio/to_thread.py
venv/lib/python3.11/site-packages/anyio-4.3.0.dist-info/entry_points.txt
venv/lib/python3.11/site-packages/anyio-4.3.0.dist-info/top_level.txt
venv/lib/python3.11/site-packages/anyio/_backends/__init__.py
venv/lib/python3.11/site-packages/anyio/_backends/_asyncio.py
venv/lib/python3.11/site-packages/anyio/_backends/_trio.py
venv/lib/python3.11/site-packages/anyio/_core/__init__.py
venv/lib/python3.11/site-packages/anyio/_core/_eventloop.py
venv/lib/python3.11/site-packages/anyio/_core/_exceptions.py
venv/lib/python3.11/site-packages/anyio/_core/_fileio.py
venv/lib/python3.11/site-packages/anyio/_core/_resources.py
venv/lib/python3.11/site-packages/anyio/_core/_signals.py
venv/lib/python3.11/site-packages/anyio/_core/_sockets.py
venv/lib/python3.11/site-packages/anyio/_core/_streams.py
venv/lib/python3.11/site-packages/anyio/_core/_subprocesses.py
venv/lib/python3.11/site-packages/anyio/_core/_synchronization.py
venv/lib/python3.11/site-packages/anyio/_core/_tasks.py
venv/lib/python3.11/site-packages/anyio/_core/_testing.py
venv/lib/python3.11/site-packages/anyio/_core/_typedattr.py
venv/lib/python3.11/site-packages/anyio/abc/__init__.py
venv/lib/python3.11/site-packages/anyio/abc/_eventloop.py
venv/lib/python3.11/site-packages/anyio/abc/_resources.py
venv/lib/python3.11/site-packages/anyio/abc/_sockets.py
venv/lib/python3.11/site-packages/anyio/abc/_streams.py
venv/lib/python3.11/site-packages/certifi-2024.2.2.dist-info/top_level.txt
venv/lib/python3.11/site-packages/h11-0.14.0.dist-info/LICENSE.txt
venv/lib/python3.11/site-packages/h11-0.14.0.dist-info/top_level.txt
venv/lib/python3.11/site-packages/httpx-0.27.0.dist-info/entry_points.txt
venv/lib/python3.11/site-packages/markdown_it_py-3.0.0.dist-info/entry_points.txt
venv/lib/python3.11/site-packages/pip-23.2.dist-info/AUTHORS.txt
venv/lib/python3.11/site-packages/pip-23.2.dist-info/LICENSE.txt
venv/lib/python3.11/site-packages/pip-23.2.dist-info/entry_points.txt
venv/lib/python3.11/site-packages/pip-23.2.dist-info/top_level.txt
venv/lib/python3.11/site-packages/pygments-2.18.0.dist-info/entry_points.txt
venv/lib/python3.11/site-packages/pyradios-2.1.0.dist-info/top_level.txt
venv/lib/python3.11/site-packages/setuptools-68.1.2.dist-info/entry_points.txt
venv/lib/python3.11/site-packages/setuptools-68.1.2.dist-info/top_level.txt
venv/lib/python3.11/site-packages/sniffio-1.3.1.dist-info/top_level.txt
venv/lib/python3.11/site-packages/wheel-0.41.0.dist-info/LICENSE.txt
venv/lib/python3.11/site-packages/wheel-0.41.0.dist-info/entry_points.txt
