Metadata-Version: 2.1
Name: tmuxradio
Version: 0.2.33
Summary: Playing globe radio station from terminal
Home-page: http://github.com/sifaw99/terminal_radio
Author: Lahcen Ouchary
Author-email: lahcen.ouchary@gmail.com
License: MIT
License-File: LICENSE.txt
